BunalabPy/__init__.py
BunalabPy/function.py
BunalabPy-0.2.dist-info/METADATA
BunalabPy-0.2.dist-info/WHEEL
BunalabPy-0.2.dist-info/top_level.txt
BunalabPy-0.2.dist-info/RECORD
