Metadata-Version: 2.1
Name: BunalabPy
Version: 0.2
Summary: A package Bunalab-System
Home-page: https://github.com/bluebox-dev/Bunalab_Platform/tree/master/BunalabPython
Author: blueboxdev
Author-email: thanakorn.vsalab@gmail.com
License: UNKNOWN
Platform: UNKNOWN
Classifier: Programming Language :: Python :: 3
Classifier: License :: OSI Approved :: MIT License
Classifier: Operating System :: OS Independent
Requires-Dist: paho-mqtt
